MANIFEST.in
NOTICE
README.rst
setup.cfg
setup.py
Smithy.egg-info/PKG-INFO
Smithy.egg-info/SOURCES.txt
Smithy.egg-info/dependency_links.txt
Smithy.egg-info/top_level.txt
bin/smithy
smithy/__init__.py
smithy/application.py
smithy/chain.py
smithy/const.py
smithy/decorators.py
smithy/exceptions.py
smithy/filelist.py
smithy/filetask.py
smithy/multitask.py
smithy/path.py
smithy/task.py
smithy/taskmanager.py
tests/001-task-tests.py
tests/002-deps-tests.py
tests/003-dep-cycle-tests.py
tests/004-build-task-tests.py
tests/005-namespace-tests.py
tests/006-rule-tests.py
tests/007-description-tests.py
tests/008-synth-task-tests.py
tests/100-file-list-tests.py
tests/101-delayed-deps-tests.py
tests/t.py